{
    "id": "k2016026",
    "level": "k",
    "year": "2016",
    "categories": [],
    "tags": [
        "k2016026"
    ],
    "question": "<p>Kemajuan teknologi di masa kini memberikan harapan bagi manusia untuk migrasi ke planet lain. Anggap di masa depan manusia telah berhasil membuat koloni di Mars. Pernyataan yang benar adalah</p><ol><li>Definisi 1 parsek tetap sebesar 206265 au (atau 206265 sa).</li><li>Peristiwa konjungsi inferior lebih jarang terjadi.</li><li>Terdapat pembagian musim menurut lintang di Mars.</li><li>Tidak ada perubahan musim di Mars.</li></ol>",
    "choices": [
        {
            "value": "0",
            "label": "1, 2, dan 3 benar"
        },
        {
            "value": "1",
            "label": "1 dan 3 benar"
        },
        {
            "value": "2",
            "label": "2 dan 4 benar"
        },
        {
            "value": "3",
            "label": "hanya 4 benar"
        },
        {
            "value": "4",
            "label": "semua benar atau semua salah"
        }
    ],
    "answer": "1",
    "explain": "<p>Penjelasan untuk masing-masing pernyataan:</p><ol><li>Definisi 1 parsek tetap atau tidak tentu bergantung kepada manusia saat itu. Jika masih menyepakati definisi satu parsek yang sekarang, ``Wikipedia: <i>One parsec is the distance at which one astronomical unit subtends an angle of one arcsecond</i>'', maka sudah sewajarnya akan tetap sebesar 206265 sa. (Pernyataan 1 <b>BENAR</b>)</li><li>Peristiwa konjungsi inferior akan lebih sering terjadi karena ada tiga planet yang mungkin mengalami konjungsi inferior dilihat dari Mars (Merkurius, Venus, dan Bumi). (Pernyataan 2 <b>SALAH</b>)</li><li>Pembagian musim di Mars bisa ditentukan bahkan sebelum manusia membuat koloni di Mars (perbedaan musim terjadi karena kemiringan sumbu rotasi Mars terhadap ekliptika). Adanya koloni meningkatkan kemungkinan penentuan musim menurut lintang secara lebih spesifik. (Pernyataan 3 <b>BENAR</b>)</li><li>Perubahan musim terjadi di Mars. (Pernyataan 4 <b>SALAH</b>)</li></ol>"
}